<?xml version="1.0" encoding="utf-8" ?>
<Patch>

    <Operation Class="PatchOperationFindMod">
        <mods>
            <li>Alpha Biomes</li>
        </mods>

        <match Class="PatchOperationSequence">
            <operations>
                <li Class="PatchOperationAddModExtension">
                    <xpath>Defs/BiomeDef[defName="AB_FeraliskInfestedJungle"]</xpath>
                    <value>
                        <li Class="FirefliesTwoO.NightlySpawningExtension">
                            <biomeEmissionRate>1.1</biomeEmissionRate>
                        </li>
                    </value>
                </li>
                <li Class="PatchOperationAddModExtension">
                    <xpath>Defs/BiomeDef[defName="AB_IdyllicMeadows"]</xpath>
                    <value>
                        <li Class="FirefliesTwoO.NightlySpawningExtension">
                            <biomeEmissionRate>1.2</biomeEmissionRate>
                        </li>
                    </value>
                </li>
            </operations>
        </match>
    </Operation>

</Patch>